[
  {
    "nombre": "MLS: Vancouver Whitecaps - San Jose Earthquakes",
    "hora": "20:30",
    "liga": "soccer",
    "logo": "logos/liga_mls.png",
    "fecha": "2026-03-21",
    "embeds": [
      {
        "nombre": "EXTRA SPORT15",
        "url": "https://5bcda32c.player-dwk.pages.dev/?get=https%3A%2F%2Fbolaloca.my%2Fplayer%2F3%2F169"
      }
    ]
  },
  {
    "nombre": "Liga Mx: UNAM Pumas - Club America",
    "hora": "21:10",
    "liga": "soccer",
    "logo": "logos/liga_mx.png",
    "fecha": "2026-03-21",
    "embeds": [
      {
        "nombre": "TUDN USA",
        "url": "https://5bcda32c.player-dwk.pages.dev/?get=https%3A%2F%2Fbolaloca.my%2Fplayer%2F3%2F68"
      },
      {
        "nombre": "TUDNMX",
        "url": "https://5bcda32c.player-dwk.pages.dev/?get=https%3A%2F%2Fbolaloca.my%2Fplayer%2F3%2F106"
      },
      {
        "nombre": "CANAL5",
        "url": "https://5bcda32c.player-dwk.pages.dev/?get=https%3A%2F%2Fbolaloca.my%2Fplayer%2F3%2F107"
      }
    ]
  },
  {
    "nombre": "Liga Endesa: Forca Lleida - Joventut Badalona",
    "hora": "05:00",
    "liga": "nba",
    "logo": "logos/nba.png",
    "fecha": "2026-03-22",
    "embeds": [
      {
        "nombre": "EXTRA SPORT1",
        "url": "https://5bcda32c.player-dwk.pages.dev/?get=https%3A%2F%2Fbolaloca.my%2Fplayer%2F3%2F155"
      }
    ]
  },
  {
    "nombre": "Eredivisie: Nijmegen - Heerenveen",
    "hora": "05:15",
    "liga": "soccer",
    "logo": "logos/liga_holanda.png",
    "fecha": "2026-03-22",
    "embeds": [
      {
        "nombre": "NL ESPN 3",
        "url": "https://5bcda32c.player-dwk.pages.dev/?get=https%3A%2F%2Fbolaloca.my%2Fplayer%2F3%2F143"
      },
      {
        "nombre": "DE Sportdigital Fussball",
        "url": "https://5bcda32c.player-dwk.pages.dev/?get=https%3A%2F%2Fbolaloca.my%2Fplayer%2F3%2F125"
      }
    ]
  },
  {
    "nombre": "Serie A: Como - Pisa",
    "hora": "05:30",
    "liga": "soccer",
    "logo": "logos/liga_italia.png",
    "fecha": "2026-03-22",
    "embeds": [
      {
        "nombre": "IT DAZN",
        "url": "https://5bcda32c.player-dwk.pages.dev/?get=https%3A%2F%2Fbolaloca.my%2Fplayer%2F3%2F137"
      },
      {
        "nombre": "DE dazn 1",
        "url": "https://5bcda32c.player-dwk.pages.dev/?get=https%3A%2F%2Fbolaloca.my%2Fplayer%2F3%2F123"
      },
      {
        "nombre": "PT SPORT 2",
        "url": "https://5bcda32c.player-dwk.pages.dev/?get=https%3A%2F%2Fbolaloca.my%2Fplayer%2F3%2F145"
      },
      {
        "nombre": "ESPN2",
        "url": "https://5bcda32c.player-dwk.pages.dev/?get=https%3A%2F%2Fbolaloca.my%2Fplayer%2F3%2F88"
      },
      {
        "nombre": "ESPN1MX",
        "url": "https://5bcda32c.player-dwk.pages.dev/?get=https%3A%2F%2Fbolaloca.my%2Fplayer%2F3%2F97"
      }
    ]
  },
  {
    "nombre": "Liga Endesa: Gran Canaria - Breogan",
    "hora": "06:00",
    "liga": "nba",
    "logo": "logos/nba.png",
    "fecha": "2026-03-22",
    "embeds": [
      {
        "nombre": "EXTRA SPORT2",
        "url": "https://5bcda32c.player-dwk.pages.dev/?get=https%3A%2F%2Fbolaloca.my%2Fplayer%2F3%2F156"
      }
    ]
  },
  {
    "nombre": "Premier League: Newcastle - Sunderland",
    "hora": "06:00",
    "liga": "soccer",
    "logo": "logos/liga_premier.png",
    "fecha": "2026-03-22",
    "embeds": [
      {
        "nombre": "canal+ foot",
        "url": "https://5bcda32c.player-dwk.pages.dev/?get=https%3A%2F%2Fbolaloca.my%2Fplayer%2F3%2F12"
      },
      {
        "nombre": "UK SKY MAIN",
        "url": "https://5bcda32c.player-dwk.pages.dev/?get=https%3A%2F%2Fbolaloca.my%2Fplayer%2F3%2F127"
      },
      {
        "nombre": "ES DAZN 1",
        "url": "https://5bcda32c.player-dwk.pages.dev/?get=https%3A%2F%2Fbolaloca.my%2Fplayer%2F3%2F56"
      },
      {
        "nombre": "DE skyde PL",
        "url": "https://5bcda32c.player-dwk.pages.dev/?get=https%3A%2F%2Fbolaloca.my%2Fplayer%2F3%2F120"
      },
      {
        "nombre": "IT FEED",
        "url": "https://5bcda32c.player-dwk.pages.dev/?get=https%3A%2F%2Fbolaloca.my%2Fplayer%2F3%2F139"
      },
      {
        "nombre": "Telemundo",
        "url": "https://5bcda32c.player-dwk.pages.dev/?get=https%3A%2F%2Fbolaloca.my%2Fplayer%2F3%2F73"
      },
      {
        "nombre": "ESPN1",
        "url": "https://5bcda32c.player-dwk.pages.dev/?get=https%3A%2F%2Fbolaloca.my%2Fplayer%2F3%2F87"
      }
    ]
  },
  {
    "nombre": "Bundesliga 2: Bochum - Holstein Kiel",
    "hora": "06:30",
    "liga": "soccer",
    "logo": "logos/liga_bundesliga.png",
    "fecha": "2026-03-22",
    "embeds": [
      {
        "nombre": "DE bundliga3",
        "url": "https://5bcda32c.player-dwk.pages.dev/?get=https%3A%2F%2Fbolaloca.my%2Fplayer%2F3%2F113"
      }
    ]
  },
  {
    "nombre": "Bundesliga 2: Dusseldorf - Hertha Berlin",
    "hora": "06:30",
    "liga": "soccer",
    "logo": "logos/liga_bundesliga.png",
    "fecha": "2026-03-22",
    "embeds": [
      {
        "nombre": "beIN max 5",
        "url": "https://5bcda32c.player-dwk.pages.dev/?get=https%3A%2F%2Fbolaloca.my%2Fplayer%2F3%2F5"
      },
      {
        "nombre": "FOXsport1 arg",
        "url": "https://5bcda32c.player-dwk.pages.dev/?get=https%3A%2F%2Fbolaloca.my%2Fplayer%2F3%2F78"
      },
      {
        "nombre": "DE bundliga4",
        "url": "https://5bcda32c.player-dwk.pages.dev/?get=https%3A%2F%2Fbolaloca.my%2Fplayer%2F3%2F114"
      }
    ]
  },
  {
    "nombre": "Bundesliga 2: Preussen Munster - Magdeburg",
    "hora": "06:30",
    "liga": "soccer",
    "logo": "logos/liga_bundesliga.png",
    "fecha": "2026-03-22",
    "embeds": [
      {
        "nombre": "DE bundliga2",
        "url": "https://5bcda32c.player-dwk.pages.dev/?get=https%3A%2F%2Fbolaloca.my%2Fplayer%2F3%2F112"
      }
    ]
  },
  {
    "nombre": "Premiership: Dundee Utd - Celtic",
    "hora": "06:30",
    "liga": "soccer",
    "logo": "logos/liga_premier.png",
    "fecha": "2026-03-22",
    "embeds": [
      {
        "nombre": "UK SKY FOOT",
        "url": "https://5bcda32c.player-dwk.pages.dev/?get=https%3A%2F%2Fbolaloca.my%2Fplayer%2F3%2F128"
      }
    ]
  },
  {
    "nombre": "Laliga: Barcelona - Rayo Vallecano",
    "hora": "07:00",
    "liga": "soccer",
    "logo": "logos/liga_española.png",
    "fecha": "2026-03-22",
    "embeds": [
      {
        "nombre": "beIN max 4",
        "url": "https://5bcda32c.player-dwk.pages.dev/?get=https%3A%2F%2Fbolaloca.my%2Fplayer%2F3%2F4"
      },
      {
        "nombre": "ES DAZN liga",
        "url": "https://5bcda32c.player-dwk.pages.dev/?get=https%3A%2F%2Fbolaloca.my%2Fplayer%2F3%2F51"
      },
      {
        "nombre": "DE dazn 2",
        "url": "https://5bcda32c.player-dwk.pages.dev/?get=https%3A%2F%2Fbolaloca.my%2Fplayer%2F3%2F124"
      },
      {
        "nombre": "ESPN Deportes",
        "url": "https://5bcda32c.player-dwk.pages.dev/?get=https%3A%2F%2Fbolaloca.my%2Fplayer%2F3%2F71"
      },
      {
        "nombre": "directv",
        "url": "https://5bcda32c.player-dwk.pages.dev/?get=https%3A%2F%2Fbolaloca.my%2Fplayer%2F3%2F94"
      }
    ]
  },
  {
    "nombre": "Laliga 2: Burgos CF - Cordoba",
    "hora": "07:00",
    "liga": "soccer",
    "logo": "logos/liga_española.png",
    "fecha": "2026-03-22",
    "embeds": [
      {
        "nombre": "ES LALIGA HYPERMOTION",
        "url": "https://5bcda32c.player-dwk.pages.dev/?get=https%3A%2F%2Fbolaloca.my%2Fplayer%2F3%2F53"
      }
    ]
  },
  {
    "nombre": "Liga AUF Uruguaya: Juventud - Albion",
    "hora": "07:00",
    "liga": "soccer",
    "logo": "logos/liga_uruguay.png",
    "fecha": "2026-03-22",
    "embeds": [
      {
        "nombre": "VTV plus",
        "url": "https://5bcda32c.player-dwk.pages.dev/?get=https%3A%2F%2Fbolaloca.my%2Fplayer%2F3%2F109"
      }
    ]
  },
  {
    "nombre": "Eredivisie: Feyenoord - Ajax",
    "hora": "07:30",
    "liga": "soccer",
    "logo": "logos/liga_holanda.png",
    "fecha": "2026-03-22",
    "embeds": [
      {
        "nombre": "NL ESPN 2",
        "url": "https://5bcda32c.player-dwk.pages.dev/?get=https%3A%2F%2Fbolaloca.my%2Fplayer%2F3%2F142"
      },
      {
        "nombre": "DE Sportdigital Fussball",
        "url": "https://5bcda32c.player-dwk.pages.dev/?get=https%3A%2F%2Fbolaloca.my%2Fplayer%2F3%2F125"
      },
      {
        "nombre": "ESPN3MX",
        "url": "https://5bcda32c.player-dwk.pages.dev/?get=https%3A%2F%2Fbolaloca.my%2Fplayer%2F3%2F99"
      }
    ]
  },
  {
    "nombre": "Eredivisie: Utrecht - G.A. Eagles",
    "hora": "07:30",
    "liga": "soccer",
    "logo": "logos/liga_holanda.png",
    "fecha": "2026-03-22",
    "embeds": [
      {
        "nombre": "NL ESPN 1",
        "url": "https://5bcda32c.player-dwk.pages.dev/?get=https%3A%2F%2Fbolaloca.my%2Fplayer%2F3%2F141"
      }
    ]
  },
  {
    "nombre": "Ligue 1: Lyon - Monaco",
    "hora": "08:00",
    "liga": "soccer",
    "logo": "logos/liga_francia.png",
    "fecha": "2026-03-22",
    "embeds": [
      {
        "nombre": "beIN 1",
        "url": "https://5bcda32c.player-dwk.pages.dev/?get=https%3A%2F%2Fbolaloca.my%2Fplayer%2F3%2F1"
      },
      {
        "nombre": "beIN En español",
        "url": "https://5bcda32c.player-dwk.pages.dev/?get=https%3A%2F%2Fbolaloca.my%2Fplayer%2F3%2F69"
      },
      {
        "nombre": "C+Live 15",
        "url": "https://5bcda32c.player-dwk.pages.dev/?get=https%3A%2F%2Fbolaloca.my%2Fplayer%2F3%2F45"
      }
    ]
  },
  {
    "nombre": "Serie A: Atalanta - Verona",
    "hora": "08:00",
    "liga": "soccer",
    "logo": "logos/liga_italia.png",
    "fecha": "2026-03-22",
    "embeds": [
      {
        "nombre": "IT DAZN",
        "url": "https://5bcda32c.player-dwk.pages.dev/?get=https%3A%2F%2Fbolaloca.my%2Fplayer%2F3%2F137"
      },
      {
        "nombre": "PT SPORT 2",
        "url": "https://5bcda32c.player-dwk.pages.dev/?get=https%3A%2F%2Fbolaloca.my%2Fplayer%2F3%2F145"
      }
    ]
  },
  {
    "nombre": "Serie A: Bologna - Lazio",
    "hora": "08:00",
    "liga": "soccer",
    "logo": "logos/liga_italia.png",
    "fecha": "2026-03-22",
    "embeds": [
      {
        "nombre": "IT FEED",
        "url": "https://5bcda32c.player-dwk.pages.dev/?get=https%3A%2F%2Fbolaloca.my%2Fplayer%2F3%2F140"
      },
      {
        "nombre": "FOX Deportes",
        "url": "https://5bcda32c.player-dwk.pages.dev/?get=https%3A%2F%2Fbolaloca.my%2Fplayer%2F3%2F70"
      },
      {
        "nombre": "ESPN1MX",
        "url": "https://5bcda32c.player-dwk.pages.dev/?get=https%3A%2F%2Fbolaloca.my%2Fplayer%2F3%2F97"
      }
    ]
  },
  {
    "nombre": "Premier League: Aston Villa - West Ham",
    "hora": "08:15",
    "liga": "soccer",
    "logo": "logos/liga_premier.png",
    "fecha": "2026-03-22",
    "embeds": [
      {
        "nombre": "canal+ foot",
        "url": "https://5bcda32c.player-dwk.pages.dev/?get=https%3A%2F%2Fbolaloca.my%2Fplayer%2F3%2F12"
      },
      {
        "nombre": "UK EPL 3PM",
        "url": "https://5bcda32c.player-dwk.pages.dev/?get=https%3A%2F%2Fbolaloca.my%2Fplayer%2F3%2F130"
      },
      {
        "nombre": "ES DAZN 1",
        "url": "https://5bcda32c.player-dwk.pages.dev/?get=https%3A%2F%2Fbolaloca.my%2Fplayer%2F3%2F56"
      },
      {
        "nombre": "DE skyde PL",
        "url": "https://5bcda32c.player-dwk.pages.dev/?get=https%3A%2F%2Fbolaloca.my%2Fplayer%2F3%2F120"
      },
      {
        "nombre": "ESPN1",
        "url": "https://5bcda32c.player-dwk.pages.dev/?get=https%3A%2F%2Fbolaloca.my%2Fplayer%2F3%2F87"
      }
    ]
  },
  {
    "nombre": "Premier League: Tottenham - Nottingham",
    "hora": "08:15",
    "liga": "soccer",
    "logo": "logos/liga_premier.png",
    "fecha": "2026-03-22",
    "embeds": [
      {
        "nombre": "canal+ sport360",
        "url": "https://5bcda32c.player-dwk.pages.dev/?get=https%3A%2F%2Fbolaloca.my%2Fplayer%2F3%2F14"
      },
      {
        "nombre": "UK SKY MAIN",
        "url": "https://5bcda32c.player-dwk.pages.dev/?get=https%3A%2F%2Fbolaloca.my%2Fplayer%2F3%2F127"
      },
      {
        "nombre": "ES DAZN 3",
        "url": "https://5bcda32c.player-dwk.pages.dev/?get=https%3A%2F%2Fbolaloca.my%2Fplayer%2F3%2F58"
      },
      {
        "nombre": "IT FEED",
        "url": "https://5bcda32c.player-dwk.pages.dev/?get=https%3A%2F%2Fbolaloca.my%2Fplayer%2F3%2F139"
      },
      {
        "nombre": "Telemundo",
        "url": "https://5bcda32c.player-dwk.pages.dev/?get=https%3A%2F%2Fbolaloca.my%2Fplayer%2F3%2F73"
      }
    ]
  },
  {
    "nombre": "Bundesliga: Mainz - Eintracht Frankfurt",
    "hora": "08:30",
    "liga": "soccer",
    "logo": "logos/liga_bundesliga.png",
    "fecha": "2026-03-22",
    "embeds": [
      {
        "nombre": "beIN max 6",
        "url": "https://5bcda32c.player-dwk.pages.dev/?get=https%3A%2F%2Fbolaloca.my%2Fplayer%2F3%2F6"
      },
      {
        "nombre": "DE dazn 1",
        "url": "https://5bcda32c.player-dwk.pages.dev/?get=https%3A%2F%2Fbolaloca.my%2Fplayer%2F3%2F123"
      },
      {
        "nombre": "ESPN2",
        "url": "https://5bcda32c.player-dwk.pages.dev/?get=https%3A%2F%2Fbolaloca.my%2Fplayer%2F3%2F88"
      },
      {
        "nombre": "DE bundliga6",
        "url": "https://5bcda32c.player-dwk.pages.dev/?get=https%3A%2F%2Fbolaloca.my%2Fplayer%2F3%2F116"
      }
    ]
  },
  {
    "nombre": "Moto3: Grand Prix du BrésilLa Moto 3 - (CH14fr)",
    "hora": "09:00",
    "liga": "soccer",
    "logo": "logos/soccer.png",
    "fecha": "2026-03-22",
    "embeds": [
      {
        "nombre": "ES DAZN F1",
        "url": "https://5bcda32c.player-dwk.pages.dev/?get=https%3A%2F%2Fbolaloca.my%2Fplayer%2F3%2F60"
      }
    ]
  },
  {
    "nombre": "Laliga: Celta Vigo - Alaves",
    "hora": "09:15",
    "liga": "soccer",
    "logo": "logos/liga_española.png",
    "fecha": "2026-03-22",
    "embeds": [
      {
        "nombre": "beIN max 4",
        "url": "https://5bcda32c.player-dwk.pages.dev/?get=https%3A%2F%2Fbolaloca.my%2Fplayer%2F3%2F4"
      },
      {
        "nombre": "ES m.laliga",
        "url": "https://5bcda32c.player-dwk.pages.dev/?get=https%3A%2F%2Fbolaloca.my%2Fplayer%2F3%2F49"
      },
      {
        "nombre": "ESPN Deportes",
        "url": "https://5bcda32c.player-dwk.pages.dev/?get=https%3A%2F%2Fbolaloca.my%2Fplayer%2F3%2F71"
      },
      {
        "nombre": "CANAL5",
        "url": "https://5bcda32c.player-dwk.pages.dev/?get=https%3A%2F%2Fbolaloca.my%2Fplayer%2F3%2F107"
      },
      {
        "nombre": "ESPN4",
        "url": "https://5bcda32c.player-dwk.pages.dev/?get=https%3A%2F%2Fbolaloca.my%2Fplayer%2F3%2F90"
      }
    ]
  },
  {
    "nombre": "Laliga 2: Mirandes - Valladolid",
    "hora": "09:15",
    "liga": "soccer",
    "logo": "logos/liga_española.png",
    "fecha": "2026-03-22",
    "embeds": [
      {
        "nombre": "ES LALIGA HYPERMOTION",
        "url": "https://5bcda32c.player-dwk.pages.dev/?get=https%3A%2F%2Fbolaloca.my%2Fplayer%2F3%2F53"
      }
    ]
  },
  {
    "nombre": "Laliga 2: Real Sociedad B - Granada CF",
    "hora": "09:15",
    "liga": "soccer",
    "logo": "logos/liga_española.png",
    "fecha": "2026-03-22",
    "embeds": [
      {
        "nombre": "ES LALIGA HYPERMOTION2",
        "url": "https://5bcda32c.player-dwk.pages.dev/?get=https%3A%2F%2Fbolaloca.my%2Fplayer%2F3%2F54"
      }
    ]
  },
  {
    "nombre": "Liga Portugal: Estoril - Rio Ave",
    "hora": "09:30",
    "liga": "soccer",
    "logo": "logos/liga_portugal.png",
    "fecha": "2026-03-22",
    "embeds": [
      {
        "nombre": "PT SPORT 1",
        "url": "https://5bcda32c.player-dwk.pages.dev/?get=https%3A%2F%2Fbolaloca.my%2Fplayer%2F3%2F144"
      }
    ]
  },
  {
    "nombre": "Eredivisie: Groningen - AZ Alkmaar",
    "hora": "09:45",
    "liga": "soccer",
    "logo": "logos/liga_holanda.png",
    "fecha": "2026-03-22",
    "embeds": [
      {
        "nombre": "NL ESPN 3",
        "url": "https://5bcda32c.player-dwk.pages.dev/?get=https%3A%2F%2Fbolaloca.my%2Fplayer%2F3%2F143"
      }
    ]
  },
  {
    "nombre": "Eredivisie: Telstar - PSV",
    "hora": "09:45",
    "liga": "soccer",
    "logo": "logos/liga_holanda.png",
    "fecha": "2026-03-22",
    "embeds": [
      {
        "nombre": "NL ESPN 1",
        "url": "https://5bcda32c.player-dwk.pages.dev/?get=https%3A%2F%2Fbolaloca.my%2Fplayer%2F3%2F141"
      },
      {
        "nombre": "DE Sportdigital Fussball",
        "url": "https://5bcda32c.player-dwk.pages.dev/?get=https%3A%2F%2Fbolaloca.my%2Fplayer%2F3%2F125"
      }
    ]
  },
  {
    "nombre": "Liga Endesa: Baskonia - Basquet Girona",
    "hora": "10:00",
    "liga": "nba",
    "logo": "logos/nba.png",
    "fecha": "2026-03-22",
    "embeds": [
      {
        "nombre": "EXTRA SPORT1",
        "url": "https://5bcda32c.player-dwk.pages.dev/?get=https%3A%2F%2Fbolaloca.my%2Fplayer%2F3%2F155"
      }
    ]
  },
  {
    "nombre": "Liga Endesa: Valencia - Granada",
    "hora": "10:00",
    "liga": "nba",
    "logo": "logos/nba.png",
    "fecha": "2026-03-22",
    "embeds": [
      {
        "nombre": "EXTRA SPORT3",
        "url": "https://5bcda32c.player-dwk.pages.dev/?get=https%3A%2F%2Fbolaloca.my%2Fplayer%2F3%2F157"
      }
    ]
  },
  {
    "nombre": "NHL: New York Rangers - Winnipeg Jets",
    "hora": "10:00",
    "liga": "nhl",
    "logo": "logos/nhl.png",
    "fecha": "2026-03-22",
    "embeds": [
      {
        "nombre": "EXTRA SPORT26",
        "url": "https://5bcda32c.player-dwk.pages.dev/?get=https%3A%2F%2Fbolaloca.my%2Fplayer%2F3%2F180"
      }
    ]
  },
  {
    "nombre": "Ligue 1: Multiplex Ligue 1 - ",
    "hora": "10:15",
    "liga": "soccer",
    "logo": "logos/liga_francia.png",
    "fecha": "2026-03-22",
    "embeds": [
      {
        "nombre": "LIGUE 1 FR",
        "url": "https://5bcda32c.player-dwk.pages.dev/?get=https%3A%2F%2Fbolaloca.my%2Fplayer%2F3%2F20"
      }
    ]
  },
  {
    "nombre": "Ligue 1: Marseille - Lille",
    "hora": "10:15",
    "liga": "soccer",
    "logo": "logos/liga_francia.png",
    "fecha": "2026-03-22",
    "embeds": [
      {
        "nombre": "LIGUE 1 FR",
        "url": "https://5bcda32c.player-dwk.pages.dev/?get=https%3A%2F%2Fbolaloca.my%2Fplayer%2F3%2F21"
      },
      {
        "nombre": "beIN En español",
        "url": "https://5bcda32c.player-dwk.pages.dev/?get=https%3A%2F%2Fbolaloca.my%2Fplayer%2F3%2F69"
      },
      {
        "nombre": "C+Live 15",
        "url": "https://5bcda32c.player-dwk.pages.dev/?get=https%3A%2F%2Fbolaloca.my%2Fplayer%2F3%2F45"
      }
    ]
  },
  {
    "nombre": "Ligue 1: Paris FC - Le Havre",
    "hora": "10:15",
    "liga": "soccer",
    "logo": "logos/liga_francia.png",
    "fecha": "2026-03-22",
    "embeds": [
      {
        "nombre": "rmc sport2",
        "url": "https://5bcda32c.player-dwk.pages.dev/?get=https%3A%2F%2Fbolaloca.my%2Fplayer%2F3%2F18"
      }
    ]
  },
  {
    "nombre": "Ligue 1: Rennes - Metz",
    "hora": "10:15",
    "liga": "soccer",
    "logo": "logos/liga_francia.png",
    "fecha": "2026-03-22",
    "embeds": [
      {
        "nombre": "LIGUE 1 FR",
        "url": "https://5bcda32c.player-dwk.pages.dev/?get=https%3A%2F%2Fbolaloca.my%2Fplayer%2F3%2F21"
      }
    ]
  },
  {
    "nombre": "Moto2: Grand Prix du BrésilLa Moto 2 - (CH14fr)",
    "hora": "10:15",
    "liga": "soccer",
    "logo": "logos/soccer.png",
    "fecha": "2026-03-22",
    "embeds": [
      {
        "nombre": "ES DAZN F1",
        "url": "https://5bcda32c.player-dwk.pages.dev/?get=https%3A%2F%2Fbolaloca.my%2Fplayer%2F3%2F60"
      }
    ]
  },
  {
    "nombre": "Bundesliga: St. Pauli - Freiburg",
    "hora": "10:30",
    "liga": "soccer",
    "logo": "logos/liga_bundesliga.png",
    "fecha": "2026-03-22",
    "embeds": [
      {
        "nombre": "beIN max 7",
        "url": "https://5bcda32c.player-dwk.pages.dev/?get=https%3A%2F%2Fbolaloca.my%2Fplayer%2F3%2F7"
      },
      {
        "nombre": "DE dazn 2",
        "url": "https://5bcda32c.player-dwk.pages.dev/?get=https%3A%2F%2Fbolaloca.my%2Fplayer%2F3%2F124"
      },
      {
        "nombre": "ESPN5",
        "url": "https://5bcda32c.player-dwk.pages.dev/?get=https%3A%2F%2Fbolaloca.my%2Fplayer%2F3%2F91"
      },
      {
        "nombre": "DE bundliga6",
        "url": "https://5bcda32c.player-dwk.pages.dev/?get=https%3A%2F%2Fbolaloca.my%2Fplayer%2F3%2F116"
      }
    ]
  },
  {
    "nombre": "D1 Féminin: Montpellier W - PSG W",
    "hora": "10:30",
    "liga": "soccer",
    "logo": "logos/soccer.png",
    "fecha": "2026-03-22",
    "embeds": [
      {
        "nombre": "canal+ foot",
        "url": "https://5bcda32c.player-dwk.pages.dev/?get=https%3A%2F%2Fbolaloca.my%2Fplayer%2F3%2F12"
      }
    ]
  },
  {
    "nombre": "Efl Cup: Arsenal - Manchester City",
    "hora": "10:30",
    "liga": "soccer",
    "logo": "logos/soccer.png",
    "fecha": "2026-03-22",
    "embeds": [
      {
        "nombre": "beIN 1",
        "url": "https://5bcda32c.player-dwk.pages.dev/?get=https%3A%2F%2Fbolaloca.my%2Fplayer%2F3%2F1"
      },
      {
        "nombre": "UK SKY MAIN",
        "url": "https://5bcda32c.player-dwk.pages.dev/?get=https%3A%2F%2Fbolaloca.my%2Fplayer%2F3%2F127"
      },
      {
        "nombre": "DE skyde PL",
        "url": "https://5bcda32c.player-dwk.pages.dev/?get=https%3A%2F%2Fbolaloca.my%2Fplayer%2F3%2F120"
      },
      {
        "nombre": "ESPN1MX",
        "url": "https://5bcda32c.player-dwk.pages.dev/?get=https%3A%2F%2Fbolaloca.my%2Fplayer%2F3%2F97"
      },
      {
        "nombre": "ESPN1",
        "url": "https://5bcda32c.player-dwk.pages.dev/?get=https%3A%2F%2Fbolaloca.my%2Fplayer%2F3%2F87"
      }
    ]
  },
  {
    "nombre": "NHL: Washington Capitals - Colorado Avalanche",
    "hora": "10:30",
    "liga": "nhl",
    "logo": "logos/nhl.png",
    "fecha": "2026-03-22",
    "embeds": [
      {
        "nombre": "beIN max 8",
        "url": "https://5bcda32c.player-dwk.pages.dev/?get=https%3A%2F%2Fbolaloca.my%2Fplayer%2F3%2F8"
      },
      {
        "nombre": "EXTRA SPORT27",
        "url": "https://5bcda32c.player-dwk.pages.dev/?get=https%3A%2F%2Fbolaloca.my%2Fplayer%2F3%2F181"
      }
    ]
  },
  {
    "nombre": "Betfred Super League: AEK Athens - Kifisia",
    "hora": "11:00",
    "liga": "soccer",
    "logo": "logos/soccer.png",
    "fecha": "2026-03-22",
    "embeds": [
      {
        "nombre": "GR SPORT 1",
        "url": "https://5bcda32c.player-dwk.pages.dev/?get=https%3A%2F%2Fbolaloca.my%2Fplayer%2F3%2F148"
      }
    ]
  },
  {
    "nombre": "Betfred Super League: Aris - OFI Crete",
    "hora": "11:00",
    "liga": "soccer",
    "logo": "logos/soccer.png",
    "fecha": "2026-03-22",
    "embeds": [
      {
        "nombre": "GR SPORT 2",
        "url": "https://5bcda32c.player-dwk.pages.dev/?get=https%3A%2F%2Fbolaloca.my%2Fplayer%2F3%2F149"
      }
    ]
  },
  {
    "nombre": "Betfred Super League: Asteras Tripolis - Panathinaikos",
    "hora": "11:00",
    "liga": "soccer",
    "logo": "logos/soccer.png",
    "fecha": "2026-03-22",
    "embeds": [
      {
        "nombre": "GR SPORT 3",
        "url": "https://5bcda32c.player-dwk.pages.dev/?get=https%3A%2F%2Fbolaloca.my%2Fplayer%2F3%2F150"
      }
    ]
  },
  {
    "nombre": "Betfred Super League: Levadiakos - Atromitos",
    "hora": "11:00",
    "liga": "soccer",
    "logo": "logos/soccer.png",
    "fecha": "2026-03-22",
    "embeds": [
      {
        "nombre": "EXTRA SPORT9",
        "url": "https://5bcda32c.player-dwk.pages.dev/?get=https%3A%2F%2Fbolaloca.my%2Fplayer%2F3%2F163"
      }
    ]
  },
  {
    "nombre": "Betfred Super League: Olympiacos Piraeus - AEL Larissa",
    "hora": "11:00",
    "liga": "soccer",
    "logo": "logos/soccer.png",
    "fecha": "2026-03-22",
    "embeds": [
      {
        "nombre": "EXTRA SPORT10",
        "url": "https://5bcda32c.player-dwk.pages.dev/?get=https%3A%2F%2Fbolaloca.my%2Fplayer%2F3%2F164"
      }
    ]
  },
  {
    "nombre": "Betfred Super League: Panetolikos - Panserraikos",
    "hora": "11:00",
    "liga": "soccer",
    "logo": "logos/soccer.png",
    "fecha": "2026-03-22",
    "embeds": [
      {
        "nombre": "EXTRA SPORT11",
        "url": "https://5bcda32c.player-dwk.pages.dev/?get=https%3A%2F%2Fbolaloca.my%2Fplayer%2F3%2F165"
      }
    ]
  },
  {
    "nombre": "Betfred Super League: Volos - PAOK",
    "hora": "11:00",
    "liga": "soccer",
    "logo": "logos/soccer.png",
    "fecha": "2026-03-22",
    "embeds": [
      {
        "nombre": "EXTRA SPORT12",
        "url": "https://5bcda32c.player-dwk.pages.dev/?get=https%3A%2F%2Fbolaloca.my%2Fplayer%2F3%2F166"
      }
    ]
  },
  {
    "nombre": "MLS: FC Cincinnati - CF Montreal",
    "hora": "11:00",
    "liga": "soccer",
    "logo": "logos/liga_mls.png",
    "fecha": "2026-03-22",
    "embeds": [
      {
        "nombre": "EXTRA SPORT7",
        "url": "https://5bcda32c.player-dwk.pages.dev/?get=https%3A%2F%2Fbolaloca.my%2Fplayer%2F3%2F161"
      }
    ]
  },
  {
    "nombre": "MLS: New York City - Inter Miami",
    "hora": "11:00",
    "liga": "soccer",
    "logo": "logos/liga_mls.png",
    "fecha": "2026-03-22",
    "embeds": [
      {
        "nombre": "EXTRA SPORT8",
        "url": "https://5bcda32c.player-dwk.pages.dev/?get=https%3A%2F%2Fbolaloca.my%2Fplayer%2F3%2F162"
      },
      {
        "nombre": "EXTRA SPORT6",
        "url": "https://5bcda32c.player-dwk.pages.dev/?get=https%3A%2F%2Fbolaloca.my%2Fplayer%2F3%2F160"
      }
    ]
  },
  {
    "nombre": "Serie A: AS Roma - Lecce",
    "hora": "11:00",
    "liga": "soccer",
    "logo": "logos/liga_italia.png",
    "fecha": "2026-03-22",
    "embeds": [
      {
        "nombre": "IT SKYCALCIO",
        "url": "https://5bcda32c.player-dwk.pages.dev/?get=https%3A%2F%2Fbolaloca.my%2Fplayer%2F3%2F138"
      },
      {
        "nombre": "ESPN2",
        "url": "https://5bcda32c.player-dwk.pages.dev/?get=https%3A%2F%2Fbolaloca.my%2Fplayer%2F3%2F88"
      }
    ]
  },
  {
    "nombre": "Laliga: Ath Bilbao - Betis",
    "hora": "11:30",
    "liga": "soccer",
    "logo": "logos/liga_española.png",
    "fecha": "2026-03-22",
    "embeds": [
      {
        "nombre": "beIN 2",
        "url": "https://5bcda32c.player-dwk.pages.dev/?get=https%3A%2F%2Fbolaloca.my%2Fplayer%2F3%2F2"
      },
      {
        "nombre": "ES DAZN liga",
        "url": "https://5bcda32c.player-dwk.pages.dev/?get=https%3A%2F%2Fbolaloca.my%2Fplayer%2F3%2F51"
      },
      {
        "nombre": "ESPN Deportes",
        "url": "https://5bcda32c.player-dwk.pages.dev/?get=https%3A%2F%2Fbolaloca.my%2Fplayer%2F3%2F71"
      },
      {
        "nombre": "directv",
        "url": "https://5bcda32c.player-dwk.pages.dev/?get=https%3A%2F%2Fbolaloca.my%2Fplayer%2F3%2F94"
      }
    ]
  },
  {
    "nombre": "Laliga 2: Las Palmas - Gijon",
    "hora": "11:30",
    "liga": "soccer",
    "logo": "logos/liga_española.png",
    "fecha": "2026-03-22",
    "embeds": [
      {
        "nombre": "ES LALIGA HYPERMOTION",
        "url": "https://5bcda32c.player-dwk.pages.dev/?get=https%3A%2F%2Fbolaloca.my%2Fplayer%2F3%2F53"
      }
    ]
  },
  {
    "nombre": "Pro League: Anderlecht - Cercle Brugge KSV",
    "hora": "11:30",
    "liga": "soccer",
    "logo": "logos/soccer.png",
    "fecha": "2026-03-22",
    "embeds": [
      {
        "nombre": "TR BeIN sport 1",
        "url": "https://5bcda32c.player-dwk.pages.dev/?get=https%3A%2F%2Fbolaloca.my%2Fplayer%2F3%2F151"
      }
    ]
  },
  {
    "nombre": "Pro League: Club Brugge KV - KV Mechelen",
    "hora": "11:30",
    "liga": "soccer",
    "logo": "logos/soccer.png",
    "fecha": "2026-03-22",
    "embeds": [
      {
        "nombre": "TR BeIN sport 2",
        "url": "https://5bcda32c.player-dwk.pages.dev/?get=https%3A%2F%2Fbolaloca.my%2Fplayer%2F3%2F152"
      }
    ]
  },
  {
    "nombre": "Pro League: Dender - Gent",
    "hora": "11:30",
    "liga": "soccer",
    "logo": "logos/soccer.png",
    "fecha": "2026-03-22",
    "embeds": [
      {
        "nombre": "EXTRA SPORT14",
        "url": "https://5bcda32c.player-dwk.pages.dev/?get=https%3A%2F%2Fbolaloca.my%2Fplayer%2F3%2F168"
      }
    ]
  },
  {
    "nombre": "Pro League: Leuven - Antwerp",
    "hora": "11:30",
    "liga": "soccer",
    "logo": "logos/soccer.png",
    "fecha": "2026-03-22",
    "embeds": [
      {
        "nombre": "EXTRA SPORT16",
        "url": "https://5bcda32c.player-dwk.pages.dev/?get=https%3A%2F%2Fbolaloca.my%2Fplayer%2F3%2F170"
      }
    ]
  },
  {
    "nombre": "Pro League: RAAL La Louviere - Genk",
    "hora": "11:30",
    "liga": "soccer",
    "logo": "logos/soccer.png",
    "fecha": "2026-03-22",
    "embeds": [
      {
        "nombre": "EXTRA SPORT15",
        "url": "https://5bcda32c.player-dwk.pages.dev/?get=https%3A%2F%2Fbolaloca.my%2Fplayer%2F3%2F169"
      }
    ]
  },
  {
    "nombre": "Pro League: St. Liege - Westerlo",
    "hora": "11:30",
    "liga": "soccer",
    "logo": "logos/soccer.png",
    "fecha": "2026-03-22",
    "embeds": [
      {
        "nombre": "BE channel1",
        "url": "https://5bcda32c.player-dwk.pages.dev/?get=https%3A%2F%2Fbolaloca.my%2Fplayer%2F3%2F153"
      }
    ]
  },
  {
    "nombre": "Pro League: St. Truiden - Royale Union SG",
    "hora": "11:30",
    "liga": "soccer",
    "logo": "logos/soccer.png",
    "fecha": "2026-03-22",
    "embeds": [
      {
        "nombre": "EXTRA SPORT13",
        "url": "https://5bcda32c.player-dwk.pages.dev/?get=https%3A%2F%2Fbolaloca.my%2Fplayer%2F3%2F167"
      }
    ]
  },
  {
    "nombre": "Pro League: Waregem - Charleroi",
    "hora": "11:30",
    "liga": "soccer",
    "logo": "logos/soccer.png",
    "fecha": "2026-03-22",
    "embeds": [
      {
        "nombre": "BE channel2",
        "url": "https://5bcda32c.player-dwk.pages.dev/?get=https%3A%2F%2Fbolaloca.my%2Fplayer%2F3%2F154"
      }
    ]
  },
  {
    "nombre": "Caf Coupes Des Confederations: Wydad AC - Olympique de Safi",
    "hora": "12:00",
    "liga": "soccer",
    "logo": "logos/soccer.png",
    "fecha": "2026-03-22",
    "embeds": [
      {
        "nombre": "beIN max 10",
        "url": "https://5bcda32c.player-dwk.pages.dev/?get=https%3A%2F%2Fbolaloca.my%2Fplayer%2F3%2F10"
      }
    ]
  },
  {
    "nombre": "Ecuador Ligapro: Tecnico U. - Ind. del Valle",
    "hora": "12:00",
    "liga": "soccer",
    "logo": "logos/soccer.png",
    "fecha": "2026-03-22",
    "embeds": [
      {
        "nombre": "Zapping sports",
        "url": "https://5bcda32c.player-dwk.pages.dev/?get=https%3A%2F%2Fbolaloca.my%2Fplayer%2F3%2F86"
      }
    ]
  },
  {
    "nombre": "Liga 1 Te Apuesto: Cajamarca - Alianza Atl.",
    "hora": "12:00",
    "liga": "soccer",
    "logo": "logos/liga_peru.png",
    "fecha": "2026-03-22",
    "embeds": [
      {
        "nombre": "Liga1MAX",
        "url": "https://5bcda32c.player-dwk.pages.dev/?get=https%3A%2F%2Fbolaloca.my%2Fplayer%2F3%2F84"
      }
    ]
  },
  {
    "nombre": "Liga De Expansion Mx: Leones Negros - Zacatecas Mineros",
    "hora": "12:00",
    "liga": "soccer",
    "logo": "logos/liga_mx.png",
    "fecha": "2026-03-22",
    "embeds": [
      {
        "nombre": "TVC Deportes",
        "url": "https://5bcda32c.player-dwk.pages.dev/?get=https%3A%2F%2Fbolaloca.my%2Fplayer%2F3%2F105"
      }
    ]
  },
  {
    "nombre": "Liga Endesa: Barcelona - Real Madrid",
    "hora": "12:00",
    "liga": "nba",
    "logo": "logos/nba.png",
    "fecha": "2026-03-22",
    "embeds": [
      {
        "nombre": "EXTRA SPORT2",
        "url": "https://5bcda32c.player-dwk.pages.dev/?get=https%3A%2F%2Fbolaloca.my%2Fplayer%2F3%2F156"
      }
    ]
  },
  {
    "nombre": "Liga Mx Women: UNAM Pumas W - Pachuca W",
    "hora": "12:00",
    "liga": "soccer",
    "logo": "logos/liga_mx.png",
    "fecha": "2026-03-22",
    "embeds": [
      {
        "nombre": "TUDN USA",
        "url": "https://5bcda32c.player-dwk.pages.dev/?get=https%3A%2F%2Fbolaloca.my%2Fplayer%2F3%2F68"
      }
    ]
  },
  {
    "nombre": "Liga Portugal: Alverca - Sporting CP",
    "hora": "12:00",
    "liga": "soccer",
    "logo": "logos/liga_portugal.png",
    "fecha": "2026-03-22",
    "embeds": [
      {
        "nombre": "beIN max 4",
        "url": "https://5bcda32c.player-dwk.pages.dev/?get=https%3A%2F%2Fbolaloca.my%2Fplayer%2F3%2F4"
      },
      {
        "nombre": "beIN max 9",
        "url": "https://5bcda32c.player-dwk.pages.dev/?get=https%3A%2F%2Fbolaloca.my%2Fplayer%2F3%2F9"
      },
      {
        "nombre": "DE Sportdigital Fussball",
        "url": "https://5bcda32c.player-dwk.pages.dev/?get=https%3A%2F%2Fbolaloca.my%2Fplayer%2F3%2F125"
      },
      {
        "nombre": "PT SPORT 2",
        "url": "https://5bcda32c.player-dwk.pages.dev/?get=https%3A%2F%2Fbolaloca.my%2Fplayer%2F3%2F145"
      }
    ]
  },
  {
    "nombre": "MotoGP: Grand Prix du BrésilLa Moto GP - (CH11fr)",
    "hora": "12:00",
    "liga": "soccer",
    "logo": "logos/soccer.png",
    "fecha": "2026-03-22",
    "embeds": [
      {
        "nombre": "ES DAZN F1",
        "url": "https://5bcda32c.player-dwk.pages.dev/?get=https%3A%2F%2Fbolaloca.my%2Fplayer%2F3%2F60"
      }
    ]
  },
  {
    "nombre": "Bundesliga: Augsburg - Stuttgart",
    "hora": "12:30",
    "liga": "soccer",
    "logo": "logos/liga_bundesliga.png",
    "fecha": "2026-03-22",
    "embeds": [
      {
        "nombre": "beIN max 6",
        "url": "https://5bcda32c.player-dwk.pages.dev/?get=https%3A%2F%2Fbolaloca.my%2Fplayer%2F3%2F6"
      },
      {
        "nombre": "DE dazn 1",
        "url": "https://5bcda32c.player-dwk.pages.dev/?get=https%3A%2F%2Fbolaloca.my%2Fplayer%2F3%2F123"
      },
      {
        "nombre": "DE bundliga6",
        "url": "https://5bcda32c.player-dwk.pages.dev/?get=https%3A%2F%2Fbolaloca.my%2Fplayer%2F3%2F116"
      }
    ]
  },
  {
    "nombre": "MLS: Minnesota United - Seattle Sounders",
    "hora": "12:30",
    "liga": "soccer",
    "logo": "logos/liga_mls.png",
    "fecha": "2026-03-22",
    "embeds": [
      {
        "nombre": "FOX Deportes",
        "url": "https://5bcda32c.player-dwk.pages.dev/?get=https%3A%2F%2Fbolaloca.my%2Fplayer%2F3%2F70"
      }
    ]
  },
  {
    "nombre": "Torneo LPF: Sarmiento Junin - Aldosivi",
    "hora": "12:30",
    "liga": "soccer",
    "logo": "logos/liga_argentina.png",
    "fecha": "2026-03-22",
    "embeds": [
      {
        "nombre": "ESPN Premium",
        "url": "https://5bcda32c.player-dwk.pages.dev/?get=https%3A%2F%2Fbolaloca.my%2Fplayer%2F3%2F76"
      }
    ]
  },
  {
    "nombre": "Caf Coupes Des Confederations: USM Alger - Maniema",
    "hora": "13:00",
    "liga": "soccer",
    "logo": "logos/soccer.png",
    "fecha": "2026-03-22",
    "embeds": [
      {
        "nombre": "beIN max 7",
        "url": "https://5bcda32c.player-dwk.pages.dev/?get=https%3A%2F%2Fbolaloca.my%2Fplayer%2F3%2F7"
      }
    ]
  },
  {
    "nombre": "Liga AUF Uruguaya: Progreso - Boston River",
    "hora": "13:00",
    "liga": "soccer",
    "logo": "logos/liga_uruguay.png",
    "fecha": "2026-03-22",
    "embeds": [
      {
        "nombre": "VTV plus",
        "url": "https://5bcda32c.player-dwk.pages.dev/?get=https%3A%2F%2Fbolaloca.my%2Fplayer%2F3%2F109"
      }
    ]
  },
  {
    "nombre": "NHL: Chicago Blackhawks - Nashville Predators",
    "hora": "13:00",
    "liga": "nhl",
    "logo": "logos/nhl.png",
    "fecha": "2026-03-22",
    "embeds": [
      {
        "nombre": "EXTRA SPORT28",
        "url": "https://5bcda32c.player-dwk.pages.dev/?get=https%3A%2F%2Fbolaloca.my%2Fplayer%2F3%2F182"
      }
    ]
  },
  {
    "nombre": "NHL: Pittsburgh Penguins - Carolina Hurricanes",
    "hora": "13:00",
    "liga": "nhl",
    "logo": "logos/nhl.png",
    "fecha": "2026-03-22",
    "embeds": [
      {
        "nombre": "EXTRA SPORT30",
        "url": "https://5bcda32c.player-dwk.pages.dev/?get=https%3A%2F%2Fbolaloca.my%2Fplayer%2F3%2F183"
      }
    ]
  },
  {
    "nombre": "Serie A Bresil: Cruzeiro - Santos",
    "hora": "13:00",
    "liga": "soccer",
    "logo": "logos/liga_italia.png",
    "fecha": "2026-03-22",
    "embeds": [
      {
        "nombre": "ES M+ Liga de Campeones",
        "url": "https://5bcda32c.player-dwk.pages.dev/?get=https%3A%2F%2Fbolaloca.my%2Fplayer%2F3%2F61"
      }
    ]
  },
  {
    "nombre": "Ligue 1: Nantes - Strasbourg",
    "hora": "13:45",
    "liga": "soccer",
    "logo": "logos/liga_francia.png",
    "fecha": "2026-03-22",
    "embeds": [
      {
        "nombre": "LIGUE 1 FR",
        "url": "https://5bcda32c.player-dwk.pages.dev/?get=https%3A%2F%2Fbolaloca.my%2Fplayer%2F3%2F20"
      },
      {
        "nombre": "beIN En español",
        "url": "https://5bcda32c.player-dwk.pages.dev/?get=https%3A%2F%2Fbolaloca.my%2Fplayer%2F3%2F69"
      },
      {
        "nombre": "IT SKYCALCIO",
        "url": "https://5bcda32c.player-dwk.pages.dev/?get=https%3A%2F%2Fbolaloca.my%2Fplayer%2F3%2F138"
      },
      {
        "nombre": "C+Live 15",
        "url": "https://5bcda32c.player-dwk.pages.dev/?get=https%3A%2F%2Fbolaloca.my%2Fplayer%2F3%2F45"
      }
    ]
  },
  {
    "nombre": "Serie A: Fiorentina - Inter",
    "hora": "13:45",
    "liga": "soccer",
    "logo": "logos/liga_italia.png",
    "fecha": "2026-03-22",
    "embeds": [
      {
        "nombre": "IT DAZN",
        "url": "https://5bcda32c.player-dwk.pages.dev/?get=https%3A%2F%2Fbolaloca.my%2Fplayer%2F3%2F137"
      },
      {
        "nombre": "UK TNT SPORT",
        "url": "https://5bcda32c.player-dwk.pages.dev/?get=https%3A%2F%2Fbolaloca.my%2Fplayer%2F3%2F126"
      },
      {
        "nombre": "ESPN2",
        "url": "https://5bcda32c.player-dwk.pages.dev/?get=https%3A%2F%2Fbolaloca.my%2Fplayer%2F3%2F88"
      },
      {
        "nombre": "ESPN1MX",
        "url": "https://5bcda32c.player-dwk.pages.dev/?get=https%3A%2F%2Fbolaloca.my%2Fplayer%2F3%2F97"
      }
    ]
  },
  {
    "nombre": "Laliga: Real Madrid - Atl. Madrid",
    "hora": "14:00",
    "liga": "soccer",
    "logo": "logos/liga_española.png",
    "fecha": "2026-03-22",
    "embeds": [
      {
        "nombre": "beIN 1",
        "url": "https://5bcda32c.player-dwk.pages.dev/?get=https%3A%2F%2Fbolaloca.my%2Fplayer%2F3%2F1"
      },
      {
        "nombre": "ES m.laliga",
        "url": "https://5bcda32c.player-dwk.pages.dev/?get=https%3A%2F%2Fbolaloca.my%2Fplayer%2F3%2F49"
      },
      {
        "nombre": "DE dazn 2",
        "url": "https://5bcda32c.player-dwk.pages.dev/?get=https%3A%2F%2Fbolaloca.my%2Fplayer%2F3%2F124"
      },
      {
        "nombre": "ESPN Deportes",
        "url": "https://5bcda32c.player-dwk.pages.dev/?get=https%3A%2F%2Fbolaloca.my%2Fplayer%2F3%2F71"
      },
      {
        "nombre": "ESPN1",
        "url": "https://5bcda32c.player-dwk.pages.dev/?get=https%3A%2F%2Fbolaloca.my%2Fplayer%2F3%2F87"
      }
    ]
  },
  {
    "nombre": "Top 14: Bordeaux Begles - Stade Toulousain",
    "hora": "14:05",
    "liga": "soccer",
    "logo": "logos/soccer.png",
    "fecha": "2026-03-22",
    "embeds": [
      {
        "nombre": "canal+",
        "url": "https://5bcda32c.player-dwk.pages.dev/?get=https%3A%2F%2Fbolaloca.my%2Fplayer%2F3%2F11"
      }
    ]
  },
  {
    "nombre": "Ecuador Ligapro: Barcelona SC - U. Catolica",
    "hora": "14:30",
    "liga": "soccer",
    "logo": "logos/soccer.png",
    "fecha": "2026-03-22",
    "embeds": [
      {
        "nombre": "Zapping sports",
        "url": "https://5bcda32c.player-dwk.pages.dev/?get=https%3A%2F%2Fbolaloca.my%2Fplayer%2F3%2F86"
      }
    ]
  },
  {
    "nombre": "Liga 1 Te Apuesto: Grau - Deportivo Garcilaso",
    "hora": "14:30",
    "liga": "soccer",
    "logo": "logos/liga_peru.png",
    "fecha": "2026-03-22",
    "embeds": [
      {
        "nombre": "Liga1MAX",
        "url": "https://5bcda32c.player-dwk.pages.dev/?get=https%3A%2F%2Fbolaloca.my%2Fplayer%2F3%2F84"
      }
    ]
  },
  {
    "nombre": "Liga Portugal: Braga - FC Porto",
    "hora": "14:30",
    "liga": "soccer",
    "logo": "logos/liga_portugal.png",
    "fecha": "2026-03-22",
    "embeds": [
      {
        "nombre": "beIN max 4",
        "url": "https://5bcda32c.player-dwk.pages.dev/?get=https%3A%2F%2Fbolaloca.my%2Fplayer%2F3%2F4"
      },
      {
        "nombre": "DE Sportdigital Fussball",
        "url": "https://5bcda32c.player-dwk.pages.dev/?get=https%3A%2F%2Fbolaloca.my%2Fplayer%2F3%2F125"
      },
      {
        "nombre": "PT SPORT 1",
        "url": "https://5bcda32c.player-dwk.pages.dev/?get=https%3A%2F%2Fbolaloca.my%2Fplayer%2F3%2F144"
      }
    ]
  },
  {
    "nombre": "MLS: Portland Timbers - Los Angeles Galaxy",
    "hora": "14:45",
    "liga": "soccer",
    "logo": "logos/liga_mls.png",
    "fecha": "2026-03-22",
    "embeds": [
      {
        "nombre": "FOX Deportes",
        "url": "https://5bcda32c.player-dwk.pages.dev/?get=https%3A%2F%2Fbolaloca.my%2Fplayer%2F3%2F70"
      }
    ]
  },
  {
    "nombre": "Torneo LPF: Estudiantes Rio Cuarto - River Plate",
    "hora": "14:45",
    "liga": "soccer",
    "logo": "logos/liga_argentina.png",
    "fecha": "2026-03-22",
    "embeds": [
      {
        "nombre": "TNT sport arg",
        "url": "https://5bcda32c.player-dwk.pages.dev/?get=https%3A%2F%2Fbolaloca.my%2Fplayer%2F3%2F75"
      },
      {
        "nombre": "ESPN5",
        "url": "https://5bcda32c.player-dwk.pages.dev/?get=https%3A%2F%2Fbolaloca.my%2Fplayer%2F3%2F91"
      }
    ]
  },
  {
    "nombre": "Liga Betplay Dimayor: Alianza - Dep. Cali",
    "hora": "15:00",
    "liga": "soccer",
    "logo": "logos/liga_colombia.png",
    "fecha": "2026-03-22",
    "embeds": [
      {
        "nombre": "WINsport+",
        "url": "https://5bcda32c.player-dwk.pages.dev/?get=https%3A%2F%2Fbolaloca.my%2Fplayer%2F3%2F81"
      }
    ]
  },
  {
    "nombre": "NBA: Denver Nuggets - Portland Trail Blazers",
    "hora": "15:00",
    "liga": "nba",
    "logo": "logos/nba.png",
    "fecha": "2026-03-22",
    "embeds": [
      {
        "nombre": "beIN 2",
        "url": "https://5bcda32c.player-dwk.pages.dev/?get=https%3A%2F%2Fbolaloca.my%2Fplayer%2F3%2F2"
      },
      {
        "nombre": "EXTRA SPORT31",
        "url": "https://5bcda32c.player-dwk.pages.dev/?get=https%3A%2F%2Fbolaloca.my%2Fplayer%2F3%2F184"
      }
    ]
  },
  {
    "nombre": "NBA: Sacramento Kings - Brooklyn Nets",
    "hora": "16:00",
    "liga": "nba",
    "logo": "logos/nba.png",
    "fecha": "2026-03-22",
    "embeds": [
      {
        "nombre": "EXTRA SPORT32",
        "url": "https://5bcda32c.player-dwk.pages.dev/?get=https%3A%2F%2Fbolaloca.my%2Fplayer%2F3%2F185"
      }
    ]
  },
  {
    "nombre": "Liga 1 Te Apuesto: Sport Boys - Sport Huancayo",
    "hora": "17:00",
    "liga": "soccer",
    "logo": "logos/liga_peru.png",
    "fecha": "2026-03-22",
    "embeds": [
      {
        "nombre": "Liga1MAX",
        "url": "https://5bcda32c.player-dwk.pages.dev/?get=https%3A%2F%2Fbolaloca.my%2Fplayer%2F3%2F84"
      }
    ]
  },
  {
    "nombre": "Liga De Expansion Mx: Jaiba Brava - Tlaxcala",
    "hora": "17:00",
    "liga": "soccer",
    "logo": "logos/liga_mx.png",
    "fecha": "2026-03-22",
    "embeds": [
      {
        "nombre": "TVC Deportes",
        "url": "https://5bcda32c.player-dwk.pages.dev/?get=https%3A%2F%2Fbolaloca.my%2Fplayer%2F3%2F105"
      }
    ]
  },
  {
    "nombre": "Liga De Expansion Mx: Tapatio - Atl. Morelia",
    "hora": "17:00",
    "liga": "soccer",
    "logo": "logos/liga_mx.png",
    "fecha": "2026-03-22",
    "embeds": [
      {
        "nombre": "ESPN4MX",
        "url": "https://5bcda32c.player-dwk.pages.dev/?get=https%3A%2F%2Fbolaloca.my%2Fplayer%2F3%2F100"
      },
      {
        "nombre": "GOL español",
        "url": "https://5bcda32c.player-dwk.pages.dev/?get=https%3A%2F%2Fbolaloca.my%2Fplayer%2F3%2F74"
      }
    ]
  },
  {
    "nombre": "Liga Mx: Pachuca - Toluca",
    "hora": "17:00",
    "liga": "soccer",
    "logo": "logos/liga_mx.png",
    "fecha": "2026-03-22",
    "embeds": [
      {
        "nombre": "TUDN USA",
        "url": "https://5bcda32c.player-dwk.pages.dev/?get=https%3A%2F%2Fbolaloca.my%2Fplayer%2F3%2F68"
      }
    ]
  },
  {
    "nombre": "Liga Mx: Santos Laguna - Puebla",
    "hora": "17:00",
    "liga": "soccer",
    "logo": "logos/liga_mx.png",
    "fecha": "2026-03-22",
    "embeds": [
      {
        "nombre": "ESPN1MX",
        "url": "https://5bcda32c.player-dwk.pages.dev/?get=https%3A%2F%2Fbolaloca.my%2Fplayer%2F3%2F97"
      }
    ]
  },
  {
    "nombre": "Liga Mx Women: Atl. San Luis W - Tigres UANL W",
    "hora": "17:00",
    "liga": "soccer",
    "logo": "logos/liga_mx.png",
    "fecha": "2026-03-22",
    "embeds": [
      {
        "nombre": "ESPN2MX",
        "url": "https://5bcda32c.player-dwk.pages.dev/?get=https%3A%2F%2Fbolaloca.my%2Fplayer%2F3%2F98"
      }
    ]
  },
  {
    "nombre": "MLS: San Diego FC - Real Salt Lake",
    "hora": "17:00",
    "liga": "soccer",
    "logo": "logos/liga_mls.png",
    "fecha": "2026-03-22",
    "embeds": [
      {
        "nombre": "EXTRA SPORT7",
        "url": "https://5bcda32c.player-dwk.pages.dev/?get=https%3A%2F%2Fbolaloca.my%2Fplayer%2F3%2F161"
      }
    ]
  },
  {
    "nombre": "NHL: Dallas Stars - Vegas Golden Knights",
    "hora": "17:00",
    "liga": "nhl",
    "logo": "logos/nhl.png",
    "fecha": "2026-03-22",
    "embeds": [
      {
        "nombre": "EXTRA SPORT33",
        "url": "https://5bcda32c.player-dwk.pages.dev/?get=https%3A%2F%2Fbolaloca.my%2Fplayer%2F3%2F186"
      }
    ]
  },
  {
    "nombre": "NHL: New York Islanders - Columbus Blue Jackets",
    "hora": "17:00",
    "liga": "nhl",
    "logo": "logos/nhl.png",
    "fecha": "2026-03-22",
    "embeds": [
      {
        "nombre": "EXTRA SPORT34",
        "url": "https://5bcda32c.player-dwk.pages.dev/?get=https%3A%2F%2Fbolaloca.my%2Fplayer%2F3%2F187"
      }
    ]
  },
  {
    "nombre": "Torneo LPF: Boca Juniors - Instituto",
    "hora": "17:00",
    "liga": "soccer",
    "logo": "logos/liga_argentina.png",
    "fecha": "2026-03-22",
    "embeds": [
      {
        "nombre": "ESPN Premium",
        "url": "https://5bcda32c.player-dwk.pages.dev/?get=https%3A%2F%2Fbolaloca.my%2Fplayer%2F3%2F76"
      },
      {
        "nombre": "ESPN1",
        "url": "https://5bcda32c.player-dwk.pages.dev/?get=https%3A%2F%2Fbolaloca.my%2Fplayer%2F3%2F87"
      },
      {
        "nombre": "DE Sportdigital Fussball",
        "url": "https://5bcda32c.player-dwk.pages.dev/?get=https%3A%2F%2Fbolaloca.my%2Fplayer%2F3%2F125"
      }
    ]
  },
  {
    "nombre": "Ecuador Ligapro: Mushuc Runa - Emelec",
    "hora": "17:15",
    "liga": "soccer",
    "logo": "logos/soccer.png",
    "fecha": "2026-03-22",
    "embeds": [
      {
        "nombre": "Zapping sports",
        "url": "https://5bcda32c.player-dwk.pages.dev/?get=https%3A%2F%2Fbolaloca.my%2Fplayer%2F3%2F86"
      }
    ]
  },
  {
    "nombre": "NBA: New York Knicks - Washington Wizards",
    "hora": "17:30",
    "liga": "nba",
    "logo": "logos/nba.png",
    "fecha": "2026-03-22",
    "embeds": [
      {
        "nombre": "EXTRA SPORT35",
        "url": "https://5bcda32c.player-dwk.pages.dev/?get=https%3A%2F%2Fbolaloca.my%2Fplayer%2F3%2F188"
      }
    ]
  },
  {
    "nombre": "Serie A Bresil: Corinthians - Flamengo RJ",
    "hora": "17:30",
    "liga": "soccer",
    "logo": "logos/liga_italia.png",
    "fecha": "2026-03-22",
    "embeds": [
      {
        "nombre": "ES M+ Liga de Campeones",
        "url": "https://5bcda32c.player-dwk.pages.dev/?get=https%3A%2F%2Fbolaloca.my%2Fplayer%2F3%2F61"
      }
    ]
  },
  {
    "nombre": "NBA: Boston Celtics - Minnesota Timberwolves",
    "hora": "18:00",
    "liga": "nba",
    "logo": "logos/nba.png",
    "fecha": "2026-03-22",
    "embeds": [
      {
        "nombre": "beIN 1",
        "url": "https://5bcda32c.player-dwk.pages.dev/?get=https%3A%2F%2Fbolaloca.my%2Fplayer%2F3%2F1"
      },
      {
        "nombre": "EXTRA SPORT36",
        "url": "https://5bcda32c.player-dwk.pages.dev/?get=https%3A%2F%2Fbolaloca.my%2Fplayer%2F3%2F189"
      }
    ]
  },
  {
    "nombre": "NHL: Anaheim Ducks - Buffalo Sabres",
    "hora": "18:00",
    "liga": "nhl",
    "logo": "logos/nhl.png",
    "fecha": "2026-03-22",
    "embeds": [
      {
        "nombre": "EXTRA SPORT37",
        "url": "https://5bcda32c.player-dwk.pages.dev/?get=https%3A%2F%2Fbolaloca.my%2Fplayer%2F3%2F190"
      }
    ]
  },
  {
    "nombre": "NHL: Calgary Flames - Tampa Bay Lightning",
    "hora": "18:00",
    "liga": "nhl",
    "logo": "logos/nhl.png",
    "fecha": "2026-03-22",
    "embeds": [
      {
        "nombre": "EXTRA SPORT38",
        "url": "https://5bcda32c.player-dwk.pages.dev/?get=https%3A%2F%2Fbolaloca.my%2Fplayer%2F3%2F191"
      }
    ]
  },
  {
    "nombre": "NBA: Phoenix Suns - Toronto Raptors",
    "hora": "19:00",
    "liga": "nba",
    "logo": "logos/nba.png",
    "fecha": "2026-03-22",
    "embeds": [
      {
        "nombre": "EXTRA SPORT39",
        "url": "https://5bcda32c.player-dwk.pages.dev/?get=https%3A%2F%2Fbolaloca.my%2Fplayer%2F3%2F192"
      }
    ]
  },
  {
    "nombre": "NHL: Utah Mammoth - Los Angeles Kings",
    "hora": "19:00",
    "liga": "nhl",
    "logo": "logos/nhl.png",
    "fecha": "2026-03-22",
    "embeds": [
      {
        "nombre": "EXTRA SPORT40",
        "url": "https://5bcda32c.player-dwk.pages.dev/?get=https%3A%2F%2Fbolaloca.my%2Fplayer%2F3%2F193"
      }
    ]
  },
  {
    "nombre": "Liga Mx: Juarez - Tigres UANL",
    "hora": "19:06",
    "liga": "soccer",
    "logo": "logos/liga_mx.png",
    "fecha": "2026-03-22",
    "embeds": [
      {
        "nombre": "FOX Deportes",
        "url": "https://5bcda32c.player-dwk.pages.dev/?get=https%3A%2F%2Fbolaloca.my%2Fplayer%2F3%2F70"
      },
      {
        "nombre": "NBC UNIVERSO",
        "url": "https://5bcda32c.player-dwk.pages.dev/?get=https%3A%2F%2Fbolaloca.my%2Fplayer%2F3%2F72"
      }
    ]
  },
  {
    "nombre": "Torneo LPF: Argentinos Jrs - Platense",
    "hora": "19:15",
    "liga": "soccer",
    "logo": "logos/liga_argentina.png",
    "fecha": "2026-03-22",
    "embeds": [
      {
        "nombre": "TNT sport arg",
        "url": "https://5bcda32c.player-dwk.pages.dev/?get=https%3A%2F%2Fbolaloca.my%2Fplayer%2F3%2F75"
      }
    ]
  },
  {
    "nombre": "Torneo LPF: Ind. Rivadavia - Rosario Central",
    "hora": "19:15",
    "liga": "soccer",
    "logo": "logos/liga_argentina.png",
    "fecha": "2026-03-22",
    "embeds": [
      {
        "nombre": "ESPN Premium",
        "url": "https://5bcda32c.player-dwk.pages.dev/?get=https%3A%2F%2Fbolaloca.my%2Fplayer%2F3%2F76"
      }
    ]
  },
  {
    "nombre": "Liga Betplay Dimayor: Chico - Deportes Tolima",
    "hora": "13:00",
    "liga": "soccer",
    "logo": "logos/liga_colombia.png",
    "fecha": "2026-03-23",
    "embeds": [
      {
        "nombre": "WINsport+",
        "url": "https://5bcda32c.player-dwk.pages.dev/?get=https%3A%2F%2Fbolaloca.my%2Fplayer%2F3%2F81"
      }
    ]
  },
  {
    "nombre": "Laliga 2: Castellon - Cultural Leonesa",
    "hora": "13:30",
    "liga": "soccer",
    "logo": "logos/liga_española.png",
    "fecha": "2026-03-23",
    "embeds": [
      {
        "nombre": "ES LALIGA HYPERMOTION",
        "url": "https://5bcda32c.player-dwk.pages.dev/?get=https%3A%2F%2Fbolaloca.my%2Fplayer%2F3%2F53"
      }
    ]
  },
  {
    "nombre": "Liga Betplay Dimayor: Santa Fe - Ind. Medellin",
    "hora": "15:10",
    "liga": "soccer",
    "logo": "logos/liga_colombia.png",
    "fecha": "2026-03-23",
    "embeds": [
      {
        "nombre": "WINsport+",
        "url": "https://5bcda32c.player-dwk.pages.dev/?get=https%3A%2F%2Fbolaloca.my%2Fplayer%2F3%2F81"
      }
    ]
  },
  {
    "nombre": "Ecuador Ligapro: Guayaquil City - Leones del Norte",
    "hora": "15:30",
    "liga": "soccer",
    "logo": "logos/soccer.png",
    "fecha": "2026-03-23",
    "embeds": [
      {
        "nombre": "Zapping sports",
        "url": "https://5bcda32c.player-dwk.pages.dev/?get=https%3A%2F%2Fbolaloca.my%2Fplayer%2F3%2F86"
      }
    ]
  },
  {
    "nombre": "Torneo LPF: Estudiantes L.P. - Central Cordoba",
    "hora": "16:00",
    "liga": "soccer",
    "logo": "logos/liga_argentina.png",
    "fecha": "2026-03-23",
    "embeds": [
      {
        "nombre": "ESPN Premium",
        "url": "https://5bcda32c.player-dwk.pages.dev/?get=https%3A%2F%2Fbolaloca.my%2Fplayer%2F3%2F76"
      }
    ]
  },
  {
    "nombre": "NBA: Detroit Pistons - Los Angeles Lakers",
    "hora": "17:00",
    "liga": "nba",
    "logo": "logos/nba.png",
    "fecha": "2026-03-23",
    "embeds": [
      {
        "nombre": "EXTRA SPORT41",
        "url": "https://5bcda32c.player-dwk.pages.dev/?get=https%3A%2F%2Fbolaloca.my%2Fplayer%2F3%2F194"
      }
    ]
  },
  {
    "nombre": "NBA: Miami Heat - San Antonio Spurs",
    "hora": "17:00",
    "liga": "nba",
    "logo": "logos/nba.png",
    "fecha": "2026-03-23",
    "embeds": [
      {
        "nombre": "beIN 3",
        "url": "https://5bcda32c.player-dwk.pages.dev/?get=https%3A%2F%2Fbolaloca.my%2Fplayer%2F3%2F3"
      },
      {
        "nombre": "EXTRA SPORT42",
        "url": "https://5bcda32c.player-dwk.pages.dev/?get=https%3A%2F%2Fbolaloca.my%2Fplayer%2F3%2F195"
      }
    ]
  },
  {
    "nombre": "NBA: Orlando Magic - Indiana Pacers",
    "hora": "17:00",
    "liga": "nba",
    "logo": "logos/nba.png",
    "fecha": "2026-03-23",
    "embeds": [
      {
        "nombre": "EXTRA SPORT43",
        "url": "https://5bcda32c.player-dwk.pages.dev/?get=https%3A%2F%2Fbolaloca.my%2Fplayer%2F3%2F196"
      }
    ]
  },
  {
    "nombre": "NBA: Philadelphia 76ers - Oklahoma City Thunder",
    "hora": "17:00",
    "liga": "nba",
    "logo": "logos/nba.png",
    "fecha": "2026-03-23",
    "embeds": [
      {
        "nombre": "EXTRA SPORT44",
        "url": "https://5bcda32c.player-dwk.pages.dev/?get=https%3A%2F%2Fbolaloca.my%2Fplayer%2F3%2F197"
      }
    ]
  },
  {
    "nombre": "Liga Betplay Dimayor: Jaguares de Cordoba - Aguilas",
    "hora": "17:20",
    "liga": "soccer",
    "logo": "logos/liga_colombia.png",
    "fecha": "2026-03-23",
    "embeds": [
      {
        "nombre": "WINsport+",
        "url": "https://5bcda32c.player-dwk.pages.dev/?get=https%3A%2F%2Fbolaloca.my%2Fplayer%2F3%2F81"
      }
    ]
  },
  {
    "nombre": "NBA: Atlanta Hawks - Memphis Grizzlies",
    "hora": "17:30",
    "liga": "nba",
    "logo": "logos/nba.png",
    "fecha": "2026-03-23",
    "embeds": [
      {
        "nombre": "EXTRA SPORT45",
        "url": "https://5bcda32c.player-dwk.pages.dev/?get=https%3A%2F%2Fbolaloca.my%2Fplayer%2F3%2F198"
      }
    ]
  },
  {
    "nombre": "NHL: New York Rangers - Ottawa Senators",
    "hora": "17:30",
    "liga": "nhl",
    "logo": "logos/nhl.png",
    "fecha": "2026-03-23",
    "embeds": [
      {
        "nombre": "EXTRA SPORT46",
        "url": "https://5bcda32c.player-dwk.pages.dev/?get=https%3A%2F%2Fbolaloca.my%2Fplayer%2F3%2F199"
      }
    ]
  },
  {
    "nombre": "Ecuador Ligapro: Aucas - Orense",
    "hora": "18:00",
    "liga": "soccer",
    "logo": "logos/soccer.png",
    "fecha": "2026-03-23",
    "embeds": [
      {
        "nombre": "Zapping sports",
        "url": "https://5bcda32c.player-dwk.pages.dev/?get=https%3A%2F%2Fbolaloca.my%2Fplayer%2F3%2F86"
      }
    ]
  },
  {
    "nombre": "NBA: Chicago Bulls - Houston Rockets",
    "hora": "18:00",
    "liga": "nba",
    "logo": "logos/nba.png",
    "fecha": "2026-03-23",
    "embeds": [
      {
        "nombre": "EXTRA SPORT47",
        "url": "https://5bcda32c.player-dwk.pages.dev/?get=https%3A%2F%2Fbolaloca.my%2Fplayer%2F3%2F200"
      }
    ]
  },
  {
    "nombre": "Torneo LPF: Huracan - Barracas Central",
    "hora": "18:15",
    "liga": "soccer",
    "logo": "logos/liga_argentina.png",
    "fecha": "2026-03-23",
    "embeds": [
      {
        "nombre": "TNT sport arg",
        "url": "https://5bcda32c.player-dwk.pages.dev/?get=https%3A%2F%2Fbolaloca.my%2Fplayer%2F3%2F75"
      }
    ]
  },
  {
    "nombre": "NBA: Utah Jazz - Toronto Raptors",
    "hora": "19:00",
    "liga": "nba",
    "logo": "logos/nba.png",
    "fecha": "2026-03-23",
    "embeds": [
      {
        "nombre": "EXTRA SPORT26",
        "url": "https://5bcda32c.player-dwk.pages.dev/?get=https%3A%2F%2Fbolaloca.my%2Fplayer%2F3%2F180"
      }
    ]
  },
  {
    "nombre": "NBA: Dallas Mavericks - Golden State Warriors",
    "hora": "19:30",
    "liga": "nba",
    "logo": "logos/nba.png",
    "fecha": "2026-03-23",
    "embeds": [
      {
        "nombre": "beIN 3",
        "url": "https://5bcda32c.player-dwk.pages.dev/?get=https%3A%2F%2Fbolaloca.my%2Fplayer%2F3%2F3"
      },
      {
        "nombre": "EXTRA SPORT27",
        "url": "https://5bcda32c.player-dwk.pages.dev/?get=https%3A%2F%2Fbolaloca.my%2Fplayer%2F3%2F181"
      }
    ]
  },
  {
    "nombre": "NBA: Portland Trail Blazers - Brooklyn Nets",
    "hora": "20:00",
    "liga": "nba",
    "logo": "logos/nba.png",
    "fecha": "2026-03-23",
    "embeds": [
      {
        "nombre": "EXTRA SPORT28",
        "url": "https://5bcda32c.player-dwk.pages.dev/?get=https%3A%2F%2Fbolaloca.my%2Fplayer%2F3%2F182"
      }
    ]
  },
  {
    "nombre": "NBA: Los Angeles Clippers - Milwaukee Bucks",
    "hora": "20:30",
    "liga": "nba",
    "logo": "logos/nba.png",
    "fecha": "2026-03-23",
    "embeds": [
      {
        "nombre": "EXTRA SPORT30",
        "url": "https://5bcda32c.player-dwk.pages.dev/?get=https%3A%2F%2Fbolaloca.my%2Fplayer%2F3%2F183"
      }
    ]
  }
]